{
  "id": "e5f6a7b8-c9d0-41e2-3456-ef5678901234",
  "eid": "evt-005",
  "user_id": "u5-67-8901-23de-f45678901234",
  "org_id": "org-6666-7777-8888-9999",
  "title": "Candidate Interview: Backend Engineer",
  "duration": 1800,
  "start_time": "2024-06-20T16:00:00Z",
  "end_time": "2024-06-20T16:30:00Z",
  "is_owner": true,
  "recording_mode": "manual",
  "connectedEntityIds": ["cand-321", "pos-654"],
  "link": "https://meet.google.com/stu-vwxy-z12",
  "content": {
    "transcript": "Interviewer: Can you explain your experience with RESTful API design? Candidate: I have built several APIs using Node.js and Express, focusing on resource modeling, versioning, and authentication. Interviewer: How do you ensure performance? Candidate: I utilize caching strategies, database indexing, and load testing.",
    "participants": ["Interviewer", "Candidate"]
  },
  "type": "EVENT",
  "summary": "Interview covered API design, performance optimization, and testing strategies. Candidate demonstrated strong experience in Node.js.",
  "recording_url": "https://storage.googleapis.com/meet-recordings/evt-005.mp4",
  "organization": {
    "id": "org-6666-7777-8888-9999",
    "name": "TalentSeekers LLC",
    "type": "RECRUITMENT",
    "org_id": "org-6666-7777-8888-9999"
  }
}
